setup.cfg
setup.py
mastool/__init__.py
mastool/extension.py
mastool/helpers.py
mastool/practices.py
mastool/test.py
mastool.egg-info/PKG-INFO
mastool.egg-info/SOURCES.txt
mastool.egg-info/dependency_links.txt
mastool.egg-info/entry_points.txt
mastool.egg-info/requires.txt
mastool.egg-info/top_level.txt