Metadata-Version: 1.1
Name: mastool
Version: 0.1.1
Summary: static analysis for bad or avoidable practices in python
Home-page: https://github.com/omaraboumrad/mastool
Author: Omar Abou Mrad
Author-email: omar.aboumrad@gmail.com
License: UNKNOWN
Download-URL: https://github.com/omaraboumrad/mastool/archive/0.1.1.tar.gz
Keywords: static,analysis,practices
Platform: UNKNOWN
